{
  "itmExtendedHeader": [],
  "itmFeatureBlocks": [
    {
      "Opcode": 7,
      "TargetType": 1,
      "Power": 0,
      "Parameter1": 98,
      "Parameter2": 5,
      "TimingMode": 2,
      "Resistance": 0,
      "Duration": 0,
      "Probability1": 100,
      "Probability2": 0,
      "Resource": {
        "character1": "\u0000",
        "character2": "\u0000",
        "character3": "\u0000",
        "character4": "\u0000",
        "character5": "\u0000",
        "character6": "\u0000",
        "character7": "\u0000",
        "character8": "\u0000"
      },
      "DiceThrown": 0,
      "DiceSides": 0,
      "SavingThrowType": 0,
      "SavingThrowBonus": 0,
      "Unknown": 0
    },
    {
      "Opcode": 7,
      "TargetType": 1,
      "Power": 0,
      "Parameter1": 93,
      "Parameter2": 4,
      "TimingMode": 2,
      "Resistance": 0,
      "Duration": 0,
      "Probability1": 100,
      "Probability2": 0,
      "Resource": {
        "character1": "\u0000",
        "character2": "\u0000",
        "character3": "\u0000",
        "character4": "\u0000",
        "character5": "\u0000",
        "character6": "\u0000",
        "character7": "\u0000",
        "character8": "\u0000"
      },
      "DiceThrown": 0,
      "DiceSides": 0,
      "SavingThrowType": 0,
      "SavingThrowBonus": 0,
      "Unknown": 0
    },
    {
      "Opcode": 7,
      "TargetType": 1,
      "Power": 0,
      "Parameter1": 27,
      "Parameter2": 0,
      "TimingMode": 2,
      "Resistance": 0,
      "Duration": 0,
      "Probability1": 100,
      "Probability2": 0,
      "Resource": {
        "character1": "\u0000",
        "character2": "\u0000",
        "character3": "\u0000",
        "character4": "\u0000",
        "character5": "\u0000",
        "character6": "\u0000",
        "character7": "\u0000",
        "character8": "\u0000"
      },
      "DiceThrown": 0,
      "DiceSides": 0,
      "SavingThrowType": 0,
      "SavingThrowBonus": 0,
      "Unknown": 0
    },
    {
      "Opcode": 0,
      "TargetType": 1,
      "Power": 0,
      "Parameter1": 8,
      "Parameter2": 1,
      "TimingMode": 2,
      "Resistance": 0,
      "Duration": 0,
      "Probability1": 100,
      "Probability2": 0,
      "Resource": {
        "character1": "\u0000",
        "character2": "\u0000",
        "character3": "\u0000",
        "character4": "\u0000",
        "character5": "\u0000",
        "character6": "\u0000",
        "character7": "\u0000",
        "character8": "\u0000"
      },
      "DiceThrown": 0,
      "DiceSides": 0,
      "SavingThrowType": 0,
      "SavingThrowBonus": 0,
      "Unknown": 0
    },
    {
      "Opcode": 59,
      "TargetType": 1,
      "Power": 0,
      "Parameter1": -2,
      "Parameter2": 0,
      "TimingMode": 2,
      "Resistance": 2,
      "Duration": 0,
      "Probability1": 100,
      "Probability2": 0,
      "Resource": {
        "character1": "\u0000",
        "character2": "\u0000",
        "character3": "\u0000",
        "character4": "\u0000",
        "character5": "\u0000",
        "character6": "\u0000",
        "character7": "\u0000",
        "character8": "\u0000"
      },
      "DiceThrown": 0,
      "DiceSides": 0,
      "SavingThrowType": 0,
      "SavingThrowBonus": 0,
      "Unknown": 0
    },
    {
      "Opcode": 90,
      "TargetType": 1,
      "Power": 0,
      "Parameter1": -1,
      "Parameter2": 0,
      "TimingMode": 2,
      "Resistance": 0,
      "Duration": 0,
      "Probability1": 100,
      "Probability2": 0,
      "Resource": {
        "character1": "\u0000",
        "character2": "\u0000",
        "character3": "\u0000",
        "character4": "\u0000",
        "character5": "\u0000",
        "character6": "\u0000",
        "character7": "\u0000",
        "character8": "\u0000"
      },
      "DiceThrown": 0,
      "DiceSides": 0,
      "SavingThrowType": 0,
      "SavingThrowBonus": 0,
      "Unknown": 0
    },
    {
      "Opcode": 91,
      "TargetType": 1,
      "Power": 0,
      "Parameter1": -1,
      "Parameter2": 0,
      "TimingMode": 2,
      "Resistance": 0,
      "Duration": 0,
      "Probability1": 100,
      "Probability2": 0,
      "Resource": {
        "character1": "\u0000",
        "character2": "\u0000",
        "character3": "\u0000",
        "character4": "\u0000",
        "character5": "\u0000",
        "character6": "\u0000",
        "character7": "\u0000",
        "character8": "\u0000"
      },
      "DiceThrown": 0,
      "DiceSides": 0,
      "SavingThrowType": 0,
      "SavingThrowBonus": 0,
      "Unknown": 0
    },
    {
      "Opcode": 92,
      "TargetType": 1,
      "Power": 0,
      "Parameter1": -4,
      "Parameter2": 0,
      "TimingMode": 2,
      "Resistance": 0,
      "Duration": 0,
      "Probability1": 100,
      "Probability2": 0,
      "Resource": {
        "character1": "\u0000",
        "character2": "\u0000",
        "character3": "\u0000",
        "character4": "\u0000",
        "character5": "\u0000",
        "character6": "\u0000",
        "character7": "\u0000",
        "character8": "\u0000"
      },
      "DiceThrown": 0,
      "DiceSides": 0,
      "SavingThrowType": 0,
      "SavingThrowBonus": 0,
      "Unknown": 0
    },
    {
      "Opcode": 28,
      "TargetType": 1,
      "Power": 0,
      "Parameter1": 10,
      "Parameter2": 0,
      "TimingMode": 2,
      "Resistance": 2,
      "Duration": 0,
      "Probability1": 100,
      "Probability2": 0,
      "Resource": {
        "character1": "\u0000",
        "character2": "\u0000",
        "character3": "\u0000",
        "character4": "\u0000",
        "character5": "\u0000",
        "character6": "\u0000",
        "character7": "\u0000",
        "character8": "\u0000"
      },
      "DiceThrown": 0,
      "DiceSides": 0,
      "SavingThrowType": 0,
      "SavingThrowBonus": 0,
      "Unknown": 0
    },
    {
      "Opcode": 142,
      "TargetType": 1,
      "Power": 0,
      "Parameter1": 0,
      "Parameter2": 25,
      "TimingMode": 2,
      "Resistance": 2,
      "Duration": 0,
      "Probability1": 100,
      "Probability2": 0,
      "Resource": {
        "character1": "\u0000",
        "character2": "\u0000",
        "character3": "\u0000",
        "character4": "\u0000",
        "character5": "\u0000",
        "character6": "\u0000",
        "character7": "\u0000",
        "character8": "\u0000"
      },
      "DiceThrown": 0,
      "DiceSides": 0,
      "SavingThrowType": 0,
      "SavingThrowBonus": 0,
      "Unknown": 0
    }
  ],
  "UnidentifiedName": {
    "Text": "Chainmail Armor",
    "Flags": "Standard",
    "Sound": "",
    "VolumeVariance": 0,
    "PitchVariance": 0,
    "Strref": 214
  },
  "IdentifiedName": {
    "Text": "Elven Chainmail of the Hand +3",
    "Flags": "Standard",
    "Sound": "",
    "VolumeVariance": 0,
    "PitchVariance": 0,
    "Strref": 8246
  },
  "ReplacementItem": "",
  "Flags": {
    "CriticalItem": false,
    "TwoHanded": false,
    "Movable": true,
    "Displayable": true,
    "Cursed": false,
    "Unknown5": true,
    "Magical": true,
    "Bow": false,
    "Silver": false,
    "ColdIron": false,
    "Stolen": false,
    "Conversable": false,
    "Unknown12": false,
    "Unknown13": false,
    "Unknown14": false,
    "Unknown15": false,
    "Unknown16": false,
    "Unknown17": false,
    "Unknown18": false,
    "Unknown19": false,
    "Unknown20": false,
    "Unknown21": false,
    "Unknown22": false,
    "Unknown23": false,
    "Unknown24": false,
    "Unknown25": false,
    "Unknown26": false,
    "Unknown27": false,
    "Unknown28": false,
    "Unknown29": false,
    "Unknown30": false,
    "Unknown31": false
  },
  "ItemType": "ChainMail",
  "Usability1": "\u0000",
  "Usability2": "\u0000",
  "Usability3": "\u0000",
  "Usability4": "\u0000",
  "Animation": "3A",
  "MinimumLevel": "\u0000",
  "Unknown": "\u0000",
  "MinimumStrength": "\b",
  "Unknown2": "\u0000",
  "MinimumStrengthBonus": "\u0000",
  "KitUsability1": "\u0000",
  "MinimumIntelligence": "\u0000",
  "KitUsability2": "\u0000",
  "MinimumDexterity": "\u0000",
  "KitUsability3": "\u0000",
  "MinimumWisdom": "\u0000",
  "KitUsability4": "\u0000",
  "MinimumConstitution": "\u0000",
  "Proficiency": "\u0000",
  "MinimumCharisma": "\u0000",
  "Unknown3": "\u0000",
  "Price": 13000,
  "StackAmount": 1,
  "InventoryIcon": "ielfchan",
  "LoreToIdentify": 18,
  "GroundIcon": "GCHAN01",
  "Weight": 15,
  "UnidentifiedDescription": {
    "Text": "Chain mail is made of interlocking metal rings.  It is always worn over a layer of padded fabric or soft leather to prevent chafing and lessen the impact of blows.  ",
    "Flags": "Standard",
    "Sound": "",
    "VolumeVariance": 0,
    "PitchVariance": 0,
    "Strref": 6673
  },
  "IdentifiedDescription": {
    "Text": "During the Golden Age between the Elves of the Seldarine's Hand and the Dwarves of Dorn Deep, special version of the illustrious elven chainmail were made that added protection against the harsh weather conditions of the north.\r\n\r\nSTATISTICS:\r\n\r\nLight Armor\r\nArmor Bonus: +8\r\nMax Dex Bonus:  +2\r\nArmor Check Penalty:  -4\r\nArcane Spell Failure:  30%\r\nResistance Bonus: +10% Cold Resistance\r\nWeight: 15 lb.",
    "Flags": "Standard",
    "Sound": "",
    "VolumeVariance": 0,
    "PitchVariance": 0,
    "Strref": 8247
  },
  "DescriptionIcon": "",
  "Enchantment": 0,
  "ExtendedHeaderOffset": 130,
  "ExtendedHeaderCount": 0,
  "FeatureBlockOffset": 130,
  "FeatureBlockEquippingIndex": 0,
  "FeatureBlockEquippingCount": 10,
  "Checksum": "A168B4F33F8C2EFD9D768531754C6FB4",
  "Filename": "00CHAN07.Itm",
  "FileType": "Itm",
  "OriginalFile": {
    "itmExtendedHeader": [],
    "itmFeatureBlocks": [
      {
        "Opcode": 7,
        "TargetType": 1,
        "Power": 0,
        "Parameter1": 98,
        "Parameter2": 5,
        "TimingMode": 2,
        "Resistance": 0,
        "Duration": 0,
        "Probability1": 100,
        "Probability2": 0,
        "Resource": {
          "character1": "\u0000",
          "character2": "\u0000",
          "character3": "\u0000",
          "character4": "\u0000",
          "character5": "\u0000",
          "character6": "\u0000",
          "character7": "\u0000",
          "character8": "\u0000"
        },
        "DiceThrown": 0,
        "DiceSides": 0,
        "SavingThrowType": 0,
        "SavingThrowBonus": 0,
        "Unknown": 0
      },
      {
        "Opcode": 7,
        "TargetType": 1,
        "Power": 0,
        "Parameter1": 93,
        "Parameter2": 4,
        "TimingMode": 2,
        "Resistance": 0,
        "Duration": 0,
        "Probability1": 100,
        "Probability2": 0,
        "Resource": {
          "character1": "\u0000",
          "character2": "\u0000",
          "character3": "\u0000",
          "character4": "\u0000",
          "character5": "\u0000",
          "character6": "\u0000",
          "character7": "\u0000",
          "character8": "\u0000"
        },
        "DiceThrown": 0,
        "DiceSides": 0,
        "SavingThrowType": 0,
        "SavingThrowBonus": 0,
        "Unknown": 0
      },
      {
        "Opcode": 7,
        "TargetType": 1,
        "Power": 0,
        "Parameter1": 27,
        "Parameter2": 0,
        "TimingMode": 2,
        "Resistance": 0,
        "Duration": 0,
        "Probability1": 100,
        "Probability2": 0,
        "Resource": {
          "character1": "\u0000",
          "character2": "\u0000",
          "character3": "\u0000",
          "character4": "\u0000",
          "character5": "\u0000",
          "character6": "\u0000",
          "character7": "\u0000",
          "character8": "\u0000"
        },
        "DiceThrown": 0,
        "DiceSides": 0,
        "SavingThrowType": 0,
        "SavingThrowBonus": 0,
        "Unknown": 0
      },
      {
        "Opcode": 0,
        "TargetType": 1,
        "Power": 0,
        "Parameter1": 8,
        "Parameter2": 1,
        "TimingMode": 2,
        "Resistance": 0,
        "Duration": 0,
        "Probability1": 100,
        "Probability2": 0,
        "Resource": {
          "character1": "\u0000",
          "character2": "\u0000",
          "character3": "\u0000",
          "character4": "\u0000",
          "character5": "\u0000",
          "character6": "\u0000",
          "character7": "\u0000",
          "character8": "\u0000"
        },
        "DiceThrown": 0,
        "DiceSides": 0,
        "SavingThrowType": 0,
        "SavingThrowBonus": 0,
        "Unknown": 0
      },
      {
        "Opcode": 59,
        "TargetType": 1,
        "Power": 0,
        "Parameter1": -2,
        "Parameter2": 0,
        "TimingMode": 2,
        "Resistance": 2,
        "Duration": 0,
        "Probability1": 100,
        "Probability2": 0,
        "Resource": {
          "character1": "\u0000",
          "character2": "\u0000",
          "character3": "\u0000",
          "character4": "\u0000",
          "character5": "\u0000",
          "character6": "\u0000",
          "character7": "\u0000",
          "character8": "\u0000"
        },
        "DiceThrown": 0,
        "DiceSides": 0,
        "SavingThrowType": 0,
        "SavingThrowBonus": 0,
        "Unknown": 0
      },
      {
        "Opcode": 90,
        "TargetType": 1,
        "Power": 0,
        "Parameter1": -1,
        "Parameter2": 0,
        "TimingMode": 2,
        "Resistance": 0,
        "Duration": 0,
        "Probability1": 100,
        "Probability2": 0,
        "Resource": {
          "character1": "\u0000",
          "character2": "\u0000",
          "character3": "\u0000",
          "character4": "\u0000",
          "character5": "\u0000",
          "character6": "\u0000",
          "character7": "\u0000",
          "character8": "\u0000"
        },
        "DiceThrown": 0,
        "DiceSides": 0,
        "SavingThrowType": 0,
        "SavingThrowBonus": 0,
        "Unknown": 0
      },
      {
        "Opcode": 91,
        "TargetType": 1,
        "Power": 0,
        "Parameter1": -1,
        "Parameter2": 0,
        "TimingMode": 2,
        "Resistance": 0,
        "Duration": 0,
        "Probability1": 100,
        "Probability2": 0,
        "Resource": {
          "character1": "\u0000",
          "character2": "\u0000",
          "character3": "\u0000",
          "character4": "\u0000",
          "character5": "\u0000",
          "character6": "\u0000",
          "character7": "\u0000",
          "character8": "\u0000"
        },
        "DiceThrown": 0,
        "DiceSides": 0,
        "SavingThrowType": 0,
        "SavingThrowBonus": 0,
        "Unknown": 0
      },
      {
        "Opcode": 92,
        "TargetType": 1,
        "Power": 0,
        "Parameter1": -4,
        "Parameter2": 0,
        "TimingMode": 2,
        "Resistance": 0,
        "Duration": 0,
        "Probability1": 100,
        "Probability2": 0,
        "Resource": {
          "character1": "\u0000",
          "character2": "\u0000",
          "character3": "\u0000",
          "character4": "\u0000",
          "character5": "\u0000",
          "character6": "\u0000",
          "character7": "\u0000",
          "character8": "\u0000"
        },
        "DiceThrown": 0,
        "DiceSides": 0,
        "SavingThrowType": 0,
        "SavingThrowBonus": 0,
        "Unknown": 0
      },
      {
        "Opcode": 28,
        "TargetType": 1,
        "Power": 0,
        "Parameter1": 10,
        "Parameter2": 0,
        "TimingMode": 2,
        "Resistance": 2,
        "Duration": 0,
        "Probability1": 100,
        "Probability2": 0,
        "Resource": {
          "character1": "\u0000",
          "character2": "\u0000",
          "character3": "\u0000",
          "character4": "\u0000",
          "character5": "\u0000",
          "character6": "\u0000",
          "character7": "\u0000",
          "character8": "\u0000"
        },
        "DiceThrown": 0,
        "DiceSides": 0,
        "SavingThrowType": 0,
        "SavingThrowBonus": 0,
        "Unknown": 0
      },
      {
        "Opcode": 142,
        "TargetType": 1,
        "Power": 0,
        "Parameter1": 0,
        "Parameter2": 25,
        "TimingMode": 2,
        "Resistance": 2,
        "Duration": 0,
        "Probability1": 100,
        "Probability2": 0,
        "Resource": {
          "character1": "\u0000",
          "character2": "\u0000",
          "character3": "\u0000",
          "character4": "\u0000",
          "character5": "\u0000",
          "character6": "\u0000",
          "character7": "\u0000",
          "character8": "\u0000"
        },
        "DiceThrown": 0,
        "DiceSides": 0,
        "SavingThrowType": 0,
        "SavingThrowBonus": 0,
        "Unknown": 0
      }
    ],
    "UnidentifiedName": {
      "Text": "Chainmail Armor",
      "Flags": "Standard",
      "Sound": "",
      "VolumeVariance": 0,
      "PitchVariance": 0,
      "Strref": 214
    },
    "IdentifiedName": {
      "Text": "Elven Chainmail of the Hand +3",
      "Flags": "Standard",
      "Sound": "",
      "VolumeVariance": 0,
      "PitchVariance": 0,
      "Strref": 8246
    },
    "ReplacementItem": "",
    "Flags": {
      "CriticalItem": false,
      "TwoHanded": false,
      "Movable": true,
      "Displayable": true,
      "Cursed": false,
      "Unknown5": true,
      "Magical": true,
      "Bow": false,
      "Silver": false,
      "ColdIron": false,
      "Stolen": false,
      "Conversable": false,
      "Unknown12": false,
      "Unknown13": false,
      "Unknown14": false,
      "Unknown15": false,
      "Unknown16": false,
      "Unknown17": false,
      "Unknown18": false,
      "Unknown19": false,
      "Unknown20": false,
      "Unknown21": false,
      "Unknown22": false,
      "Unknown23": false,
      "Unknown24": false,
      "Unknown25": false,
      "Unknown26": false,
      "Unknown27": false,
      "Unknown28": false,
      "Unknown29": false,
      "Unknown30": false,
      "Unknown31": false
    },
    "ItemType": "ChainMail",
    "Usability1": "\u0000",
    "Usability2": "\u0000",
    "Usability3": "\u0000",
    "Usability4": "\u0000",
    "Animation": "3A",
    "MinimumLevel": "\u0000",
    "Unknown": "\u0000",
    "MinimumStrength": "\b",
    "Unknown2": "\u0000",
    "MinimumStrengthBonus": "\u0000",
    "KitUsability1": "\u0000",
    "MinimumIntelligence": "\u0000",
    "KitUsability2": "\u0000",
    "MinimumDexterity": "\u0000",
    "KitUsability3": "\u0000",
    "MinimumWisdom": "\u0000",
    "KitUsability4": "\u0000",
    "MinimumConstitution": "\u0000",
    "Proficiency": "\u0000",
    "MinimumCharisma": "\u0000",
    "Unknown3": "\u0000",
    "Price": 13000,
    "StackAmount": 1,
    "InventoryIcon": "ielfchan",
    "LoreToIdentify": 18,
    "GroundIcon": "GCHAN01",
    "Weight": 15,
    "UnidentifiedDescription": {
      "Text": "Chain mail is made of interlocking metal rings.  It is always worn over a layer of padded fabric or soft leather to prevent chafing and lessen the impact of blows.  ",
      "Flags": "Standard",
      "Sound": "",
      "VolumeVariance": 0,
      "PitchVariance": 0,
      "Strref": 6673
    },
    "IdentifiedDescription": {
      "Text": "During the Golden Age between the Elves of the Seldarine's Hand and the Dwarves of Dorn Deep, special version of the illustrious elven chainmail were made that added protection against the harsh weather conditions of the north.\r\n\r\nSTATISTICS:\r\n\r\nLight Armor\r\nArmor Bonus: +8\r\nMax Dex Bonus:  +2\r\nArmor Check Penalty:  -4\r\nArcane Spell Failure:  30%\r\nResistance Bonus: +10% Cold Resistance\r\nWeight: 15 lb.",
      "Flags": "Standard",
      "Sound": "",
      "VolumeVariance": 0,
      "PitchVariance": 0,
      "Strref": 8247
    },
    "DescriptionIcon": "",
    "Enchantment": 0,
    "ExtendedHeaderOffset": 130,
    "ExtendedHeaderCount": 0,
    "FeatureBlockOffset": 130,
    "FeatureBlockEquippingIndex": 0,
    "FeatureBlockEquippingCount": 10,
    "Checksum": "A168B4F33F8C2EFD9D768531754C6FB4",
    "Filename": null,
    "FileType": "Itm",
    "OriginalFile": null
  }
}