{
  "itmExtendedHeader": [
    {
      "itmFeatureBlocks": [
        {
          "Opcode": 139,
          "TargetType": 1,
          "Power": 0,
          "Parameter1": 16233,
          "Parameter2": 0,
          "TimingMode": 1,
          "Resistance": 0,
          "Duration": 0,
          "Probability1": 100,
          "Probability2": 0,
          "Resource": {
            "character1": "\u0000",
            "character2": "\u0000",
            "character3": "\u0000",
            "character4": "\u0000",
            "character5": "\u0000",
            "character6": "\u0000",
            "character7": "\u0000",
            "character8": "\u0000"
          },
          "DiceThrown": 0,
          "DiceSides": 0,
          "SavingThrowType": 0,
          "SavingThrowBonus": 0,
          "Unknown": 0
        },
        {
          "Opcode": 402,
          "TargetType": 1,
          "Power": 2,
          "Parameter1": 0,
          "Parameter2": 0,
          "TimingMode": 4,
          "Resistance": 3,
          "Duration": 1200,
          "Probability1": 100,
          "Probability2": 0,
          "Resource": {
            "character1": "E",
            "character2": "f",
            "character3": "f",
            "character4": "D",
            "character5": "M",
            "character6": "2",
            "character7": "\u0000",
            "character8": "\u0000"
          },
          "DiceThrown": 0,
          "DiceSides": 0,
          "SavingThrowType": 0,
          "SavingThrowBonus": 0,
          "Unknown": 0
        },
        {
          "Opcode": 135,
          "TargetType": 1,
          "Power": 2,
          "Parameter1": 0,
          "Parameter2": 0,
          "TimingMode": 0,
          "Resistance": 3,
          "Duration": 1200,
          "Probability1": 100,
          "Probability2": 0,
          "Resource": {
            "character1": "S",
            "character2": "C",
            "character3": "H",
            "character4": "i",
            "character5": "s",
            "character6": "t",
            "character7": "a",
            "character8": "c"
          },
          "DiceThrown": 0,
          "DiceSides": 0,
          "SavingThrowType": 0,
          "SavingThrowBonus": 0,
          "Unknown": 0
        },
        {
          "Opcode": 233,
          "TargetType": 1,
          "Power": 2,
          "Parameter1": 0,
          "Parameter2": 4,
          "TimingMode": 1,
          "Resistance": 3,
          "Duration": 0,
          "Probability1": 100,
          "Probability2": 0,
          "Resource": {
            "character1": "\u0000",
            "character2": "\u0000",
            "character3": "\u0000",
            "character4": "\u0000",
            "character5": "\u0000",
            "character6": "\u0000",
            "character7": "\u0000",
            "character8": "\u0000"
          },
          "DiceThrown": 0,
          "DiceSides": 0,
          "SavingThrowType": 0,
          "SavingThrowBonus": 0,
          "Unknown": 0
        },
        {
          "Opcode": 233,
          "TargetType": 1,
          "Power": 2,
          "Parameter1": 0,
          "Parameter2": 31,
          "TimingMode": 1,
          "Resistance": 3,
          "Duration": 0,
          "Probability1": 100,
          "Probability2": 0,
          "Resource": {
            "character1": "\u0000",
            "character2": "\u0000",
            "character3": "\u0000",
            "character4": "\u0000",
            "character5": "\u0000",
            "character6": "\u0000",
            "character7": "\u0000",
            "character8": "\u0000"
          },
          "DiceThrown": 0,
          "DiceSides": 0,
          "SavingThrowType": 0,
          "SavingThrowBonus": 0,
          "Unknown": 0
        },
        {
          "Opcode": 233,
          "TargetType": 1,
          "Power": 2,
          "Parameter1": 0,
          "Parameter2": 1,
          "TimingMode": 1,
          "Resistance": 3,
          "Duration": 0,
          "Probability1": 100,
          "Probability2": 0,
          "Resource": {
            "character1": "\u0000",
            "character2": "\u0000",
            "character3": "\u0000",
            "character4": "\u0000",
            "character5": "\u0000",
            "character6": "\u0000",
            "character7": "\u0000",
            "character8": "\u0000"
          },
          "DiceThrown": 0,
          "DiceSides": 0,
          "SavingThrowType": 0,
          "SavingThrowBonus": 0,
          "Unknown": 0
        },
        {
          "Opcode": 111,
          "TargetType": 1,
          "Power": 2,
          "Parameter1": 0,
          "Parameter2": 0,
          "TimingMode": 0,
          "Resistance": 3,
          "Duration": 1200,
          "Probability1": 100,
          "Probability2": 0,
          "Resource": {
            "character1": "0",
            "character2": "0",
            "character3": "C",
            "character4": "W",
            "character5": "Y",
            "character6": "U",
            "character7": "T",
            "character8": "2"
          },
          "DiceThrown": 0,
          "DiceSides": 0,
          "SavingThrowType": 0,
          "SavingThrowBonus": 0,
          "Unknown": 0
        },
        {
          "Opcode": 139,
          "TargetType": 1,
          "Power": 2,
          "Parameter1": 2505,
          "Parameter2": 0,
          "TimingMode": 4,
          "Resistance": 3,
          "Duration": 1100,
          "Probability1": 100,
          "Probability2": 0,
          "Resource": {
            "character1": "\u0000",
            "character2": "\u0000",
            "character3": "\u0000",
            "character4": "\u0000",
            "character5": "\u0000",
            "character6": "\u0000",
            "character7": "\u0000",
            "character8": "\u0000"
          },
          "DiceThrown": 0,
          "DiceSides": 0,
          "SavingThrowType": 0,
          "SavingThrowBonus": 0,
          "Unknown": 0
        }
      ],
      "AttackType": "\u0003",
      "IdentificationRequirement": "\u0000",
      "Location": "\u0003",
      "AlternaticeDiceSides": "\u0000",
      "UseIcon": {
        "character1": "I",
        "character2": "P",
        "character3": "o",
        "character4": "t",
        "character5": "n",
        "character6": "S",
        "character7": "B",
        "character8": "\u0000"
      },
      "TargetType": "\u0005",
      "TargetCount": "\u0000",
      "Range": 1,
      "ProjectileType": 0,
      "AlternaticeDiceThrown": 0,
      "Speed": 0,
      "AlternaticeDamageBonus": 0,
      "Thac0Bonus": 0,
      "DiceSides": 6,
      "PrimaryType": 0,
      "DiceThrown": 0,
      "SecondaryType": 0,
      "DamageBonus": 0,
      "DamageType": 1,
      "FeatureBlockCount": 8,
      "FeatureBlockOffset": 0,
      "Charges": 1,
      "ChargeDepletionBehaviour": 1,
      "Flags": 0,
      "Unknown": 0,
      "ProjectileAnimation": 1,
      "MeleeAnimation1": 34,
      "MeleeAnimation2": 33,
      "MeleeAnimation3": 33,
      "IsBowArrow": 0,
      "IsCrossbowBolt": 0,
      "IsMiscProjectile": 0
    }
  ],
  "itmFeatureBlocks": [],
  "UnidentifiedName": {
    "Text": "Strange Brew",
    "Flags": "Standard",
    "Sound": "",
    "VolumeVariance": 0,
    "PitchVariance": 0,
    "Strref": 28326
  },
  "IdentifiedName": {
    "Text": "Sabotaged Histachii Brew",
    "Flags": "Standard",
    "Sound": "",
    "VolumeVariance": 0,
    "PitchVariance": 0,
    "Strref": 28327
  },
  "ReplacementItem": "",
  "Flags": {
    "CriticalItem": true,
    "TwoHanded": false,
    "Movable": true,
    "Displayable": true,
    "Cursed": false,
    "Unknown5": true,
    "Magical": true,
    "Bow": false,
    "Silver": false,
    "ColdIron": false,
    "Stolen": false,
    "Conversable": true,
    "Unknown12": false,
    "Unknown13": false,
    "Unknown14": false,
    "Unknown15": false,
    "Unknown16": false,
    "Unknown17": false,
    "Unknown18": false,
    "Unknown19": false,
    "Unknown20": false,
    "Unknown21": false,
    "Unknown22": false,
    "Unknown23": false,
    "Unknown24": false,
    "Unknown25": false,
    "Unknown26": false,
    "Unknown27": false,
    "Unknown28": false,
    "Unknown29": false,
    "Unknown30": false,
    "Unknown31": false
  },
  "ItemType": "Potions",
  "Usability1": "\u0000",
  "Usability2": "\u0000",
  "Usability3": "\u0000",
  "Usability4": "\u0000",
  "Animation": "  ",
  "MinimumLevel": "\u0000",
  "Unknown": "\u0000",
  "MinimumStrength": "\u0000",
  "Unknown2": "\u0000",
  "MinimumStrengthBonus": "\u0000",
  "KitUsability1": "\u0000",
  "MinimumIntelligence": "\u0000",
  "KitUsability2": "\u0000",
  "MinimumDexterity": "\u0000",
  "KitUsability3": "\u0000",
  "MinimumWisdom": "\u0000",
  "KitUsability4": "\u0000",
  "MinimumConstitution": "\u0000",
  "Proficiency": "\u0000",
  "MinimumCharisma": "\u0000",
  "Unknown3": "\u0000",
  "Price": 400,
  "StackAmount": 5,
  "InventoryIcon": "IPotnSB",
  "LoreToIdentify": 10,
  "GroundIcon": "GPOTN01",
  "Weight": 1,
  "UnidentifiedDescription": {
    "Text": "This liquid appears to be the concoction of yuan-ti venom and various herbs and roots.",
    "Flags": "Standard",
    "Sound": "",
    "VolumeVariance": 0,
    "PitchVariance": 0,
    "Strref": 28328
  },
  "IdentifiedDescription": {
    "Text": "This liquid, specially prepared by one of the yuan-ti priestesses, is the concoction of yuan-ti venom and various herbs and roots, including the modified mandrake root that you planted.\r\n\r\nSTATISTICS:\r\n\r\nThis enchanted broth transforms anyone who ingests it into a special yuan-ti histachii for a period of four hours.  While transformed, the imbiber maintains mental clarity and control over their facilities, but is otherwise indistinguishable from regular histachii.\r\n\r\nWeight: 1 lb.",
    "Flags": "Standard",
    "Sound": "",
    "VolumeVariance": 0,
    "PitchVariance": 0,
    "Strref": 28329
  },
  "DescriptionIcon": "",
  "Enchantment": 0,
  "ExtendedHeaderOffset": 130,
  "ExtendedHeaderCount": 1,
  "FeatureBlockOffset": 186,
  "FeatureBlockEquippingIndex": 0,
  "FeatureBlockEquippingCount": 0,
  "Checksum": "C52EDEA3357649449846EBAE80E5B0E6",
  "Filename": "61POTNSB.Itm",
  "FileType": "Itm",
  "OriginalFile": {
    "itmExtendedHeader": [
      {
        "itmFeatureBlocks": [
          {
            "Opcode": 139,
            "TargetType": 1,
            "Power": 0,
            "Parameter1": 16233,
            "Parameter2": 0,
            "TimingMode": 1,
            "Resistance": 0,
            "Duration": 0,
            "Probability1": 100,
            "Probability2": 0,
            "Resource": {
              "character1": "\u0000",
              "character2": "\u0000",
              "character3": "\u0000",
              "character4": "\u0000",
              "character5": "\u0000",
              "character6": "\u0000",
              "character7": "\u0000",
              "character8": "\u0000"
            },
            "DiceThrown": 0,
            "DiceSides": 0,
            "SavingThrowType": 0,
            "SavingThrowBonus": 0,
            "Unknown": 0
          },
          {
            "Opcode": 402,
            "TargetType": 1,
            "Power": 2,
            "Parameter1": 0,
            "Parameter2": 0,
            "TimingMode": 4,
            "Resistance": 3,
            "Duration": 1200,
            "Probability1": 100,
            "Probability2": 0,
            "Resource": {
              "character1": "E",
              "character2": "f",
              "character3": "f",
              "character4": "D",
              "character5": "M",
              "character6": "2",
              "character7": "\u0000",
              "character8": "\u0000"
            },
            "DiceThrown": 0,
            "DiceSides": 0,
            "SavingThrowType": 0,
            "SavingThrowBonus": 0,
            "Unknown": 0
          },
          {
            "Opcode": 135,
            "TargetType": 1,
            "Power": 2,
            "Parameter1": 0,
            "Parameter2": 0,
            "TimingMode": 0,
            "Resistance": 3,
            "Duration": 1200,
            "Probability1": 100,
            "Probability2": 0,
            "Resource": {
              "character1": "S",
              "character2": "C",
              "character3": "H",
              "character4": "i",
              "character5": "s",
              "character6": "t",
              "character7": "a",
              "character8": "c"
            },
            "DiceThrown": 0,
            "DiceSides": 0,
            "SavingThrowType": 0,
            "SavingThrowBonus": 0,
            "Unknown": 0
          },
          {
            "Opcode": 233,
            "TargetType": 1,
            "Power": 2,
            "Parameter1": 0,
            "Parameter2": 4,
            "TimingMode": 1,
            "Resistance": 3,
            "Duration": 0,
            "Probability1": 100,
            "Probability2": 0,
            "Resource": {
              "character1": "\u0000",
              "character2": "\u0000",
              "character3": "\u0000",
              "character4": "\u0000",
              "character5": "\u0000",
              "character6": "\u0000",
              "character7": "\u0000",
              "character8": "\u0000"
            },
            "DiceThrown": 0,
            "DiceSides": 0,
            "SavingThrowType": 0,
            "SavingThrowBonus": 0,
            "Unknown": 0
          },
          {
            "Opcode": 233,
            "TargetType": 1,
            "Power": 2,
            "Parameter1": 0,
            "Parameter2": 31,
            "TimingMode": 1,
            "Resistance": 3,
            "Duration": 0,
            "Probability1": 100,
            "Probability2": 0,
            "Resource": {
              "character1": "\u0000",
              "character2": "\u0000",
              "character3": "\u0000",
              "character4": "\u0000",
              "character5": "\u0000",
              "character6": "\u0000",
              "character7": "\u0000",
              "character8": "\u0000"
            },
            "DiceThrown": 0,
            "DiceSides": 0,
            "SavingThrowType": 0,
            "SavingThrowBonus": 0,
            "Unknown": 0
          },
          {
            "Opcode": 233,
            "TargetType": 1,
            "Power": 2,
            "Parameter1": 0,
            "Parameter2": 1,
            "TimingMode": 1,
            "Resistance": 3,
            "Duration": 0,
            "Probability1": 100,
            "Probability2": 0,
            "Resource": {
              "character1": "\u0000",
              "character2": "\u0000",
              "character3": "\u0000",
              "character4": "\u0000",
              "character5": "\u0000",
              "character6": "\u0000",
              "character7": "\u0000",
              "character8": "\u0000"
            },
            "DiceThrown": 0,
            "DiceSides": 0,
            "SavingThrowType": 0,
            "SavingThrowBonus": 0,
            "Unknown": 0
          },
          {
            "Opcode": 111,
            "TargetType": 1,
            "Power": 2,
            "Parameter1": 0,
            "Parameter2": 0,
            "TimingMode": 0,
            "Resistance": 3,
            "Duration": 1200,
            "Probability1": 100,
            "Probability2": 0,
            "Resource": {
              "character1": "0",
              "character2": "0",
              "character3": "C",
              "character4": "W",
              "character5": "Y",
              "character6": "U",
              "character7": "T",
              "character8": "2"
            },
            "DiceThrown": 0,
            "DiceSides": 0,
            "SavingThrowType": 0,
            "SavingThrowBonus": 0,
            "Unknown": 0
          },
          {
            "Opcode": 139,
            "TargetType": 1,
            "Power": 2,
            "Parameter1": 2505,
            "Parameter2": 0,
            "TimingMode": 4,
            "Resistance": 3,
            "Duration": 1100,
            "Probability1": 100,
            "Probability2": 0,
            "Resource": {
              "character1": "\u0000",
              "character2": "\u0000",
              "character3": "\u0000",
              "character4": "\u0000",
              "character5": "\u0000",
              "character6": "\u0000",
              "character7": "\u0000",
              "character8": "\u0000"
            },
            "DiceThrown": 0,
            "DiceSides": 0,
            "SavingThrowType": 0,
            "SavingThrowBonus": 0,
            "Unknown": 0
          }
        ],
        "AttackType": "\u0003",
        "IdentificationRequirement": "\u0000",
        "Location": "\u0003",
        "AlternaticeDiceSides": "\u0000",
        "UseIcon": {
          "character1": "I",
          "character2": "P",
          "character3": "o",
          "character4": "t",
          "character5": "n",
          "character6": "S",
          "character7": "B",
          "character8": "\u0000"
        },
        "TargetType": "\u0005",
        "TargetCount": "\u0000",
        "Range": 1,
        "ProjectileType": 0,
        "AlternaticeDiceThrown": 0,
        "Speed": 0,
        "AlternaticeDamageBonus": 0,
        "Thac0Bonus": 0,
        "DiceSides": 6,
        "PrimaryType": 0,
        "DiceThrown": 0,
        "SecondaryType": 0,
        "DamageBonus": 0,
        "DamageType": 1,
        "FeatureBlockCount": 8,
        "FeatureBlockOffset": 0,
        "Charges": 1,
        "ChargeDepletionBehaviour": 1,
        "Flags": 0,
        "Unknown": 0,
        "ProjectileAnimation": 1,
        "MeleeAnimation1": 34,
        "MeleeAnimation2": 33,
        "MeleeAnimation3": 33,
        "IsBowArrow": 0,
        "IsCrossbowBolt": 0,
        "IsMiscProjectile": 0
      }
    ],
    "itmFeatureBlocks": [],
    "UnidentifiedName": {
      "Text": "Strange Brew",
      "Flags": "Standard",
      "Sound": "",
      "VolumeVariance": 0,
      "PitchVariance": 0,
      "Strref": 28326
    },
    "IdentifiedName": {
      "Text": "Sabotaged Histachii Brew",
      "Flags": "Standard",
      "Sound": "",
      "VolumeVariance": 0,
      "PitchVariance": 0,
      "Strref": 28327
    },
    "ReplacementItem": "",
    "Flags": {
      "CriticalItem": true,
      "TwoHanded": false,
      "Movable": true,
      "Displayable": true,
      "Cursed": false,
      "Unknown5": true,
      "Magical": true,
      "Bow": false,
      "Silver": false,
      "ColdIron": false,
      "Stolen": false,
      "Conversable": true,
      "Unknown12": false,
      "Unknown13": false,
      "Unknown14": false,
      "Unknown15": false,
      "Unknown16": false,
      "Unknown17": false,
      "Unknown18": false,
      "Unknown19": false,
      "Unknown20": false,
      "Unknown21": false,
      "Unknown22": false,
      "Unknown23": false,
      "Unknown24": false,
      "Unknown25": false,
      "Unknown26": false,
      "Unknown27": false,
      "Unknown28": false,
      "Unknown29": false,
      "Unknown30": false,
      "Unknown31": false
    },
    "ItemType": "Potions",
    "Usability1": "\u0000",
    "Usability2": "\u0000",
    "Usability3": "\u0000",
    "Usability4": "\u0000",
    "Animation": "  ",
    "MinimumLevel": "\u0000",
    "Unknown": "\u0000",
    "MinimumStrength": "\u0000",
    "Unknown2": "\u0000",
    "MinimumStrengthBonus": "\u0000",
    "KitUsability1": "\u0000",
    "MinimumIntelligence": "\u0000",
    "KitUsability2": "\u0000",
    "MinimumDexterity": "\u0000",
    "KitUsability3": "\u0000",
    "MinimumWisdom": "\u0000",
    "KitUsability4": "\u0000",
    "MinimumConstitution": "\u0000",
    "Proficiency": "\u0000",
    "MinimumCharisma": "\u0000",
    "Unknown3": "\u0000",
    "Price": 400,
    "StackAmount": 5,
    "InventoryIcon": "IPotnSB",
    "LoreToIdentify": 10,
    "GroundIcon": "GPOTN01",
    "Weight": 1,
    "UnidentifiedDescription": {
      "Text": "This liquid appears to be the concoction of yuan-ti venom and various herbs and roots.",
      "Flags": "Standard",
      "Sound": "",
      "VolumeVariance": 0,
      "PitchVariance": 0,
      "Strref": 28328
    },
    "IdentifiedDescription": {
      "Text": "This liquid, specially prepared by one of the yuan-ti priestesses, is the concoction of yuan-ti venom and various herbs and roots, including the modified mandrake root that you planted.\r\n\r\nSTATISTICS:\r\n\r\nThis enchanted broth transforms anyone who ingests it into a special yuan-ti histachii for a period of four hours.  While transformed, the imbiber maintains mental clarity and control over their facilities, but is otherwise indistinguishable from regular histachii.\r\n\r\nWeight: 1 lb.",
      "Flags": "Standard",
      "Sound": "",
      "VolumeVariance": 0,
      "PitchVariance": 0,
      "Strref": 28329
    },
    "DescriptionIcon": "",
    "Enchantment": 0,
    "ExtendedHeaderOffset": 130,
    "ExtendedHeaderCount": 1,
    "FeatureBlockOffset": 186,
    "FeatureBlockEquippingIndex": 0,
    "FeatureBlockEquippingCount": 0,
    "Checksum": "C52EDEA3357649449846EBAE80E5B0E6",
    "Filename": null,
    "FileType": "Itm",
    "OriginalFile": null
  }
}